.bzrignore
.flake8
.gitignore
.mailmap
.testr.conf
.travis.yml
AUTHORS
HACKING.md
LICENSE
MANIFEST.in
Makefile
README.md
TODO
download-license-data.py
goals.md
key-package-versions.json
key-package-versions.py
next.py
renamed-tags.json
renamed-tags.py
setup.cfg
setup.py
spdx.json
tag-status.py
tag-status.yaml
buildtools/update-readme.py
debian/apply-multiarch-hints.1
debian/changelog
debian/control
debian/copyright
debian/deb-scrub-obsolete.1
debian/debianize.1
debian/docs
debian/gitlab-ci.yml
debian/lintian-brush.1
debian/lintian-brush.bash-completion
debian/lintian-brush.conf.5
debian/lintian-brush.zsh-completion
debian/manpages
debian/rules
debian/source/format
debian/source/lintian-overrides
debian/tests/control
debian/tests/tool-testsuite
debian/upstream/metadata
doc/fixer-writing-guide.rst
fixers/ancient-maintscript-entry.py
fixers/ancient-python-version-field.py
fixers/autotools-pkg-config-macro-not-cross-compilation-safe.py
fixers/binary-control-field-duplicates-source.py
fixers/build-depends-on-build-essential.py
fixers/build-depends-on-obsolete-package.py
fixers/built-using-for-golang.py
fixers/changelog-has-duplicate-line.py
fixers/comma-separated-files-in-dep5-copyright.py
fixers/common-license.py
fixers/control-file-with-CRLF-EOLs.sh
fixers/copyright-continued-lines-with-space.py
fixers/copyright-has-crs.sh
fixers/copyright-missing-upstream-info.py
fixers/copyright-refers-to-symlink-license.py
fixers/debhelper-but-no-misc-depends.py
fixers/debhelper-compat-wrong-field.py
fixers/debhelper-tools-from-autotools-dev-are-deprecated.py
fixers/debian-changelog-file-contains-obsolete-user-emacs-settings.sh
fixers/debian-changelog-has-wrong-day-of-week.py
fixers/debian-changelog-line-too-long.py
fixers/debian-control-has-empty-field.py
fixers/debian-control-has-obsolete-dbg-package.py
fixers/debian-control-has-unusual-field-spacing.py
fixers/debian-pycompat-is-obsolete.sh
fixers/debian-pyversions-is-obsolete.py
lintian_brush.egg-info/PKG-INFO
lintian_brush.egg-info/SOURCES.txt
lintian_brush.egg-info/dependency_links.txt
lintian_brush.egg-info/entry_points.txt
lintian_brush.egg-info/requires.txt
lintian_brush.egg-info/top_level.txt
tests/copyright-missing-upstream-info/doap/message
tests/copyright-missing-upstream-info/doap/in/blah.doap
tests/copyright-missing-upstream-info/doap/in/debian/copyright
tests/copyright-missing-upstream-info/doap/out/blah.doap
tests/copyright-missing-upstream-info/doap/out/debian/copyright
tests/copyright-missing-upstream-info/from-upstream-metadata/message
tests/copyright-missing-upstream-info/from-upstream-metadata/in/debian/copyright
tests/copyright-missing-upstream-info/from-upstream-metadata/in/debian/upstream/metadata
tests/copyright-missing-upstream-info/from-upstream-metadata/out/debian/copyright
tests/copyright-missing-upstream-info/from-upstream-metadata/out/debian/upstream/metadata
