Metadata-Version: 1.2
Name: lintian-brush
Version: 0.107
Summary: Automatic lintian issue fixer
Home-page: https://salsa.debian.org/jelmer/lintian-brush
Author: Jelmer Vernooij
Author-email: jelmer@debian.org
License: UNKNOWN
Project-URL: Repository, https://salsa.debian.org/jelmer/lintian-brush
Platform: UNKNOWN
